Metadata-Version: 2.1
Name: pyEventLogger
Version: 1.0.1
Summary: Simple Python Library for making customized Logs of certain events that occur in a program.
Home-page: https://github.com/Sid72020123/pyEventLogger/
Author: Siddhesh Chavan
Author-email: siddheshchavan2020@gmail.com
License: MIT
Keywords: log event log-event
Platform: UNKNOWN
Classifier: Development Status :: 5 - Production/Stable
Classifier: Intended Audience :: Education
Classifier: Operating System :: OS Independent
Classifier: License :: OSI Approved :: MIT License
Classifier: Programming Language :: Python :: 3
